README.rst
setup.cfg
setup.py
stackinawsgi/__init__.py
stackinawsgi/exceptions.py
stackinawsgi.egg-info/PKG-INFO
stackinawsgi.egg-info/SOURCES.txt
stackinawsgi.egg-info/dependency_links.txt
stackinawsgi.egg-info/requires.txt
stackinawsgi.egg-info/top_level.txt
stackinawsgi.egg-info/zip-safe
stackinawsgi/admin/__init__.py
stackinawsgi/admin/admin.py
stackinawsgi/session/__init__.py
stackinawsgi/session/service.py
stackinawsgi/session/session.py
stackinawsgi/test/__init__.py
stackinawsgi/test/helpers.py
stackinawsgi/test/test_admin_admin.py
stackinawsgi/test/test_session_service.py
stackinawsgi/test/test_session_session.py
stackinawsgi/test/test_wsgi_app.py
stackinawsgi/test/test_wsgi_request.py
stackinawsgi/test/test_wsgi_response.py
stackinawsgi/wsgi/__init__.py
stackinawsgi/wsgi/app.py
stackinawsgi/wsgi/request.py
stackinawsgi/wsgi/response.py