Metadata-Version: 1.1
Name: stackinawsgi
Version: 0.1
Summary: WSGI loader for StackInABox
Home-page: https://github.com/TestInABox/stackInAWSGI
Author: Benjamen R. Meyer
Author-email: bm_witness@yahoo.com
License: Apache License 2.0
Platform: UNKNOWN
Classifier: Intended Audience :: Developers
Classifier: License :: OSI Approved :: MIT License
Classifier: Topic :: Software Development :: Testing
